[
  {
    "ContainingType": "MovieWebApp.Presentation.Controllers.Admin.GenreController",
    "Method": "CreateGenre",
    "RelativePath": "api/admin/genres",
    "HttpMethod": "POST",
    "IsController": true,
    "Order": 0,
    "Parameters": [
      {
        "Name": "genreDto",
        "Type": "MovieWebApp.Application.DTOs.GenreDto",
        "IsRequired": true
      }
    ],
    "ReturnTypes": []
  },
  {
    "ContainingType": "MovieWebApp.Presentation.Controllers.Admin.GenreController",
    "Method": "DeleteGenre",
    "RelativePath": "api/admin/genres/{id}",
    "HttpMethod": "DELETE",
    "IsController": true,
    "Order": 0,
    "Parameters": [
      {
        "Name": "id",
        "Type": "System.Int32",
        "IsRequired": true
      }
    ],
    "ReturnTypes": []
  },
  {
    "ContainingType": "MovieWebApp.Presentation.Controllers.Admin.MovieController",
    "Method": "CreateMovie",
    "RelativePath": "api/admin/movies",
    "HttpMethod": "POST",
    "IsController": true,
    "Order": 0,
    "Parameters": [
      {
        "Name": "MovieName",
        "Type": "System.String",
        "IsRequired": false
      },
      {
        "Name": "Description",
        "Type": "System.String",
        "IsRequired": false
      },
      {
        "Name": "ReleaseYear",
        "Type": "System.Int32",
        "IsRequired": false
      },
      {
        "Name": "Country",
        "Type": "System.String",
        "IsRequired": false
      },
      {
        "Name": "Language",
        "Type": "System.String",
        "IsRequired": false
      },
      {
        "Name": "GenreIds",
        "Type": "System.Collections.Generic.List\u00601[[System.Int32, System.Private.CoreLib, Version=9.0.0.0, Culture=neutral, PublicKeyToken=7cec85d7bea7798e]]",
        "IsRequired": false
      },
      {
        "Name": "PosterFile",
        "Type": "Microsoft.AspNetCore.Http.IFormFile",
        "IsRequired": false
      },
      {
        "Name": "VideoFile",
        "Type": "Microsoft.AspNetCore.Http.IFormFile",
        "IsRequired": false
      }
    ],
    "ReturnTypes": []
  },
  {
    "ContainingType": "MovieWebApp.Presentation.Controllers.Admin.MovieController",
    "Method": "UpdateMovie",
    "RelativePath": "api/admin/movies/{id}",
    "HttpMethod": "PUT",
    "IsController": true,
    "Order": 0,
    "Parameters": [
      {
        "Name": "id",
        "Type": "System.Int32",
        "IsRequired": true
      },
      {
        "Name": "MovieName",
        "Type": "System.String",
        "IsRequired": false
      },
      {
        "Name": "Description",
        "Type": "System.String",
        "IsRequired": false
      },
      {
        "Name": "ReleaseYear",
        "Type": "System.Int32",
        "IsRequired": false
      },
      {
        "Name": "Country",
        "Type": "System.String",
        "IsRequired": false
      },
      {
        "Name": "Language",
        "Type": "System.String",
        "IsRequired": false
      },
      {
        "Name": "GenreIds",
        "Type": "System.Collections.Generic.List\u00601[[System.Int32, System.Private.CoreLib, Version=9.0.0.0, Culture=neutral, PublicKeyToken=7cec85d7bea7798e]]",
        "IsRequired": false
      },
      {
        "Name": "PosterFile",
        "Type": "Microsoft.AspNetCore.Http.IFormFile",
        "IsRequired": false
      },
      {
        "Name": "VideoFile",
        "Type": "Microsoft.AspNetCore.Http.IFormFile",
        "IsRequired": false
      }
    ],
    "ReturnTypes": []
  },
  {
    "ContainingType": "MovieWebApp.Presentation.Controllers.Admin.MovieController",
    "Method": "DeleteMovie",
    "RelativePath": "api/admin/movies/{id}",
    "HttpMethod": "DELETE",
    "IsController": true,
    "Order": 0,
    "Parameters": [
      {
        "Name": "id",
        "Type": "System.Int32",
        "IsRequired": true
      }
    ],
    "ReturnTypes": []
  },
  {
    "ContainingType": "MovieWebApp.Presentation.Controllers.Admin.MovieController",
    "Method": "GetAllMovies",
    "RelativePath": "api/admin/movies/all",
    "HttpMethod": "GET",
    "IsController": true,
    "Order": 0,
    "Parameters": [],
    "ReturnTypes": []
  },
  {
    "ContainingType": "AuthController",
    "Method": "GetById",
    "RelativePath": "api/Auth/{id}",
    "HttpMethod": "GET",
    "IsController": true,
    "Order": 0,
    "Parameters": [
      {
        "Name": "id",
        "Type": "System.Int32",
        "IsRequired": true
      }
    ],
    "ReturnTypes": []
  },
  {
    "ContainingType": "AuthController",
    "Method": "ChangePassword",
    "RelativePath": "api/Auth/change-password",
    "HttpMethod": "POST",
    "IsController": true,
    "Order": 0,
    "Parameters": [
      {
        "Name": "dto",
        "Type": "MovieWebApp.Application.DTOs.ChangePasswordDto",
        "IsRequired": true
      }
    ],
    "ReturnTypes": []
  },
  {
    "ContainingType": "AuthController",
    "Method": "Login",
    "RelativePath": "api/Auth/login",
    "HttpMethod": "POST",
    "IsController": true,
    "Order": 0,
    "Parameters": [
      {
        "Name": "model",
        "Type": "MovieWebApp.Application.DTOs.Auth.LoginDto",
        "IsRequired": true
      }
    ],
    "ReturnTypes": []
  },
  {
    "ContainingType": "AuthController",
    "Method": "Register",
    "RelativePath": "api/Auth/register",
    "HttpMethod": "POST",
    "IsController": true,
    "Order": 0,
    "Parameters": [
      {
        "Name": "model",
        "Type": "MovieWebApp.Application.DTOs.Auth.RegisterDto",
        "IsRequired": true
      }
    ],
    "ReturnTypes": []
  },
  {
    "ContainingType": "MovieWebApp.Presentation.Controllers.Admin.CommentController",
    "Method": "GetAllComments",
    "RelativePath": "api/Comment",
    "HttpMethod": "GET",
    "IsController": true,
    "Order": 0,
    "Parameters": [],
    "ReturnTypes": []
  },
  {
    "ContainingType": "MovieWebApp.Presentation.Controllers.Admin.CommentController",
    "Method": "DeleteComment",
    "RelativePath": "api/Comment/{commentId}",
    "HttpMethod": "DELETE",
    "IsController": true,
    "Order": 0,
    "Parameters": [
      {
        "Name": "commentId",
        "Type": "System.Int32",
        "IsRequired": true
      }
    ],
    "ReturnTypes": []
  },
  {
    "ContainingType": "MovieWebApp.Presentation.Controllers.Client.CommentController",
    "Method": "CreateComment",
    "RelativePath": "api/comments",
    "HttpMethod": "POST",
    "IsController": true,
    "Order": 0,
    "Parameters": [
      {
        "Name": "createCommentDto",
        "Type": "MovieWebApp.Application.DTOs.CreateCommentDto",
        "IsRequired": true
      }
    ],
    "ReturnTypes": []
  },
  {
    "ContainingType": "MovieWebApp.Presentation.Controllers.Client.CommentController",
    "Method": "UpdateComment",
    "RelativePath": "api/comments/{id}",
    "HttpMethod": "PUT",
    "IsController": true,
    "Order": 0,
    "Parameters": [
      {
        "Name": "id",
        "Type": "System.Int32",
        "IsRequired": true
      },
      {
        "Name": "updateCommentDto",
        "Type": "MovieWebApp.Application.DTOs.UpdateCommentDto",
        "IsRequired": true
      }
    ],
    "ReturnTypes": []
  },
  {
    "ContainingType": "MovieWebApp.Presentation.Controllers.Client.CommentController",
    "Method": "DeleteComment",
    "RelativePath": "api/comments/{id}",
    "HttpMethod": "DELETE",
    "IsController": true,
    "Order": 0,
    "Parameters": [
      {
        "Name": "id",
        "Type": "System.Int32",
        "IsRequired": true
      }
    ],
    "ReturnTypes": []
  },
  {
    "ContainingType": "MovieWebApp.Presentation.Controllers.Client.CommentController",
    "Method": "GetComment",
    "RelativePath": "api/comments/{id}",
    "HttpMethod": "GET",
    "IsController": true,
    "Order": 0,
    "Parameters": [
      {
        "Name": "id",
        "Type": "System.Int32",
        "IsRequired": true
      }
    ],
    "ReturnTypes": []
  },
  {
    "ContainingType": "MovieWebApp.Presentation.Controllers.Client.CommentController",
    "Method": "GetCommentsByMovie",
    "RelativePath": "api/comments/movie/{movieId}",
    "HttpMethod": "GET",
    "IsController": true,
    "Order": 0,
    "Parameters": [
      {
        "Name": "movieId",
        "Type": "System.Int32",
        "IsRequired": true
      }
    ],
    "ReturnTypes": []
  },
  {
    "ContainingType": "MovieWebApp.Presentation.Controllers.Client.CommentController",
    "Method": "GetCommentsByUser",
    "RelativePath": "api/comments/user/{userId}",
    "HttpMethod": "GET",
    "IsController": true,
    "Order": 0,
    "Parameters": [
      {
        "Name": "userId",
        "Type": "System.Int32",
        "IsRequired": true
      }
    ],
    "ReturnTypes": []
  },
  {
    "ContainingType": "MovieWebApp.Presentation.Controllers.Admin.DashboardController",
    "Method": "GetDashboardStats",
    "RelativePath": "api/Dashboard/stats",
    "HttpMethod": "GET",
    "IsController": true,
    "Order": 0,
    "Parameters": [],
    "ReturnTypes": []
  },
  {
    "ContainingType": "MovieWebApp.Presentation.Controllers.Client.FavoriteController",
    "Method": "GetFavoritesByUser",
    "RelativePath": "api/favorites",
    "HttpMethod": "GET",
    "IsController": true,
    "Order": 0,
    "Parameters": [],
    "ReturnTypes": []
  },
  {
    "ContainingType": "MovieWebApp.Presentation.Controllers.Client.FavoriteController",
    "Method": "AddFavorite",
    "RelativePath": "api/favorites",
    "HttpMethod": "POST",
    "IsController": true,
    "Order": 0,
    "Parameters": [
      {
        "Name": "dto",
        "Type": "MovieWebApp.Application.DTOs.FavoriteDto",
        "IsRequired": true
      }
    ],
    "ReturnTypes": []
  },
  {
    "ContainingType": "MovieWebApp.Presentation.Controllers.Client.FavoriteController",
    "Method": "RemoveFavorite",
    "RelativePath": "api/favorites/{movieId}",
    "HttpMethod": "DELETE",
    "IsController": true,
    "Order": 0,
    "Parameters": [
      {
        "Name": "movieId",
        "Type": "System.Int32",
        "IsRequired": true
      }
    ],
    "ReturnTypes": []
  },
  {
    "ContainingType": "MovieWebApp.Presentation.Controllers.Client.GenreController",
    "Method": "GetAll",
    "RelativePath": "api/genres",
    "HttpMethod": "GET",
    "IsController": true,
    "Order": 0,
    "Parameters": [],
    "ReturnTypes": []
  },
  {
    "ContainingType": "MovieWebApp.Presentation.Controllers.Client.GenreController",
    "Method": "GetById",
    "RelativePath": "api/genres/{id}",
    "HttpMethod": "GET",
    "IsController": true,
    "Order": 0,
    "Parameters": [
      {
        "Name": "id",
        "Type": "System.Int32",
        "IsRequired": true
      }
    ],
    "ReturnTypes": []
  },
  {
    "ContainingType": "MovieWebApp.Presentation.Controllers.Client.MovieController",
    "Method": "GetAll",
    "RelativePath": "api/movies",
    "HttpMethod": "GET",
    "IsController": true,
    "Order": 0,
    "Parameters": [],
    "ReturnTypes": []
  },
  {
    "ContainingType": "MovieWebApp.Presentation.Controllers.Client.MovieController",
    "Method": "GetById",
    "RelativePath": "api/movies/{id}",
    "HttpMethod": "GET",
    "IsController": true,
    "Order": 0,
    "Parameters": [
      {
        "Name": "id",
        "Type": "System.Int32",
        "IsRequired": true
      }
    ],
    "ReturnTypes": []
  },
  {
    "ContainingType": "MovieWebApp.Presentation.Controllers.Client.MovieController",
    "Method": "GetPaged",
    "RelativePath": "api/movies/paged",
    "HttpMethod": "GET",
    "IsController": true,
    "Order": 0,
    "Parameters": [
      {
        "Name": "pageNumber",
        "Type": "System.Int32",
        "IsRequired": false
      },
      {
        "Name": "pageSize",
        "Type": "System.Int32",
        "IsRequired": false
      },
      {
        "Name": "search",
        "Type": "System.String",
        "IsRequired": false
      },
      {
        "Name": "genre",
        "Type": "System.String",
        "IsRequired": false
      }
    ],
    "ReturnTypes": []
  },
  {
    "ContainingType": "MovieWebApp.Presentation.Controllers.Client.MovieController",
    "Method": "SearchMovies",
    "RelativePath": "api/movies/search",
    "HttpMethod": "GET",
    "IsController": true,
    "Order": 0,
    "Parameters": [
      {
        "Name": "keyword",
        "Type": "System.String",
        "IsRequired": false
      }
    ],
    "ReturnTypes": [
      {
        "Type": "System.Collections.Generic.IEnumerable\u00601[[MovieWebApp.Application.DTOs.MovieDto, MovieWebApp, Version=1.0.0.0, Culture=neutral, PublicKeyToken=null]]",
        "MediaTypes": [
          "text/plain",
          "application/json",
          "text/json"
        ],
        "StatusCode": 200
      }
    ]
  },
  {
    "ContainingType": "MovieWebApp.Presentation.Controllers.Admin.RatingController",
    "Method": "GetAllRatings",
    "RelativePath": "api/Rating",
    "HttpMethod": "GET",
    "IsController": true,
    "Order": 0,
    "Parameters": [],
    "ReturnTypes": []
  },
  {
    "ContainingType": "MovieWebApp.Presentation.Controllers.Admin.RatingController",
    "Method": "DeleteRating",
    "RelativePath": "api/Rating/{ratingId}",
    "HttpMethod": "DELETE",
    "IsController": true,
    "Order": 0,
    "Parameters": [
      {
        "Name": "ratingId",
        "Type": "System.Int32",
        "IsRequired": true
      }
    ],
    "ReturnTypes": []
  },
  {
    "ContainingType": "MovieWebApp.Presentation.Controllers.Client.RatingController",
    "Method": "CreateRating",
    "RelativePath": "api/ratings",
    "HttpMethod": "POST",
    "IsController": true,
    "Order": 0,
    "Parameters": [
      {
        "Name": "createRatingDto",
        "Type": "MovieWebApp.Application.DTOs.CreateRatingDto",
        "IsRequired": true
      }
    ],
    "ReturnTypes": []
  },
  {
    "ContainingType": "MovieWebApp.Presentation.Controllers.Client.RatingController",
    "Method": "UpdateRating",
    "RelativePath": "api/ratings/{id}",
    "HttpMethod": "PUT",
    "IsController": true,
    "Order": 0,
    "Parameters": [
      {
        "Name": "id",
        "Type": "System.Int32",
        "IsRequired": true
      },
      {
        "Name": "updateRatingDto",
        "Type": "MovieWebApp.Application.DTOs.UpdateRatingDto",
        "IsRequired": true
      }
    ],
    "ReturnTypes": []
  },
  {
    "ContainingType": "MovieWebApp.Presentation.Controllers.Client.RatingController",
    "Method": "DeleteRating",
    "RelativePath": "api/ratings/{id}",
    "HttpMethod": "DELETE",
    "IsController": true,
    "Order": 0,
    "Parameters": [
      {
        "Name": "id",
        "Type": "System.Int32",
        "IsRequired": true
      }
    ],
    "ReturnTypes": []
  },
  {
    "ContainingType": "MovieWebApp.Presentation.Controllers.Client.RatingController",
    "Method": "GetRating",
    "RelativePath": "api/ratings/{id}",
    "HttpMethod": "GET",
    "IsController": true,
    "Order": 0,
    "Parameters": [
      {
        "Name": "id",
        "Type": "System.Int32",
        "IsRequired": true
      }
    ],
    "ReturnTypes": []
  },
  {
    "ContainingType": "MovieWebApp.Presentation.Controllers.Client.RatingController",
    "Method": "GetRatingsByMovie",
    "RelativePath": "api/ratings/movie/{movieId}",
    "HttpMethod": "GET",
    "IsController": true,
    "Order": 0,
    "Parameters": [
      {
        "Name": "movieId",
        "Type": "System.Int32",
        "IsRequired": true
      }
    ],
    "ReturnTypes": []
  },
  {
    "ContainingType": "MovieWebApp.Presentation.Controllers.Client.RatingController",
    "Method": "GetAverageRating",
    "RelativePath": "api/ratings/movie/{movieId}/average",
    "HttpMethod": "GET",
    "IsController": true,
    "Order": 0,
    "Parameters": [
      {
        "Name": "movieId",
        "Type": "System.Int32",
        "IsRequired": true
      }
    ],
    "ReturnTypes": []
  },
  {
    "ContainingType": "MovieWebApp.Presentation.Controllers.Client.RatingController",
    "Method": "GetUserRatingForMovie",
    "RelativePath": "api/ratings/movie/{movieId}/user",
    "HttpMethod": "GET",
    "IsController": true,
    "Order": 0,
    "Parameters": [
      {
        "Name": "movieId",
        "Type": "System.Int32",
        "IsRequired": true
      }
    ],
    "ReturnTypes": []
  },
  {
    "ContainingType": "MovieWebApp.Presentation.Controllers.Client.RatingController",
    "Method": "GetRatingsByUser",
    "RelativePath": "api/ratings/user/{userId}",
    "HttpMethod": "GET",
    "IsController": true,
    "Order": 0,
    "Parameters": [
      {
        "Name": "userId",
        "Type": "System.Int32",
        "IsRequired": true
      }
    ],
    "ReturnTypes": []
  },
  {
    "ContainingType": "MovieWebApp.Presentation.Controllers.Admin.UserController",
    "Method": "GetAllUsers",
    "RelativePath": "api/User",
    "HttpMethod": "GET",
    "IsController": true,
    "Order": 0,
    "Parameters": [],
    "ReturnTypes": []
  },
  {
    "ContainingType": "MovieWebApp.Presentation.Controllers.Admin.UserController",
    "Method": "GetUserById",
    "RelativePath": "api/User/{userId}",
    "HttpMethod": "GET",
    "IsController": true,
    "Order": 0,
    "Parameters": [
      {
        "Name": "userId",
        "Type": "System.Int32",
        "IsRequired": true
      }
    ],
    "ReturnTypes": []
  },
  {
    "ContainingType": "MovieWebApp.Presentation.Controllers.Admin.UserController",
    "Method": "DeleteUser",
    "RelativePath": "api/User/{userId}",
    "HttpMethod": "DELETE",
    "IsController": true,
    "Order": 0,
    "Parameters": [
      {
        "Name": "userId",
        "Type": "System.Int32",
        "IsRequired": true
      }
    ],
    "ReturnTypes": []
  },
  {
    "ContainingType": "MovieWebApp.Presentation.Controllers.Admin.UserController",
    "Method": "UpdateUserRole",
    "RelativePath": "api/User/{userId}/role",
    "HttpMethod": "PUT",
    "IsController": true,
    "Order": 0,
    "Parameters": [
      {
        "Name": "userId",
        "Type": "System.Int32",
        "IsRequired": true
      },
      {
        "Name": "dto",
        "Type": "MovieWebApp.Application.DTOs.UpdateUserRoleDto",
        "IsRequired": true
      }
    ],
    "ReturnTypes": []
  }
]